Metadata-Version: 2.1
Name: weatherbymoe
Version: 1.0.0
Summary: Weather forecast data
Home-page: https://github.com/MoeTahech
Author: Moe ElTahech
Author-email: Mohamed.tahech10@outlook.com
License: MIT
Keywords: weather,forecast,openweather
Classifier: Development Status :: 3 - Alpha
Classifier: Intended Audience :: Developers
Classifier: Topic :: Software Development :: Build Tools
Classifier: License :: OSI Approved :: MIT License
Classifier: Programming Language :: Python :: 3.5
Classifier: Programming Language :: Python :: 3.6
Classifier: Programming Language :: Python :: 3.7
Classifier: Programming Language :: Python :: 3.8
Classifier: Programming Language :: Python :: 3.9
Classifier: Programming Language :: Python :: 3.10
Classifier: Programming Language :: Python :: 3.11
Classifier: Programming Language :: Python :: 3.12
Requires-Dist: requests
